{"version": 0.6, "generator": "Overpass API 0.7.62.5 1bd436f1", "osm3s": {"timestamp_osm_base": "2025-02-15T00:16:33Z", "copyright": "The data included in this document is from www.openstreetmap.org. The data is made available under ODbL."}, "elements": [{"type": "node", "id": 419495538, "lat": 18.67795, "lon": 12.797983}, {"type": "node", "id": 419495781, "lat": 18.677167, "lon": 12.79655}, {"type": "node", "id": 419495782, "lat": 18.675517, "lon": 12.79385}, {"type": "node", "id": 419495783, "lat": 18.673767, "lon": 12.79045}, {"type": "node", "id": 419495784, "lat": 18.6719, "lon": 12.78705}, {"type": "node", "id": 419495785, "lat": 18.67105, "lon": 12.7852}, {"type": "node", "id": 419495786, "lat": 18.66955, "lon": 12.781517}, {"type": "node", "id": 419495787, "lat": 18.667767, "lon": 12.77805}, {"type": "node", "id": 419495788, "lat": 18.66695, "lon": 12.776217}, {"type": "node", "id": 419495789, "lat": 18.66525, "lon": 12.772067}, {"type": "node", "id": 419495790, "lat": 18.663583, "lon": 12.767817}, {"type": "node", "id": 419495791, "lat": 18.662967, "lon": 12.765583}, {"type": "node", "id": 419495792, "lat": 18.662283, "lon": 12.763533}, {"type": "node", "id": 419495793, "lat": 18.661167, "lon": 12.75895}, {"type": "node", "id": 419495794, "lat": 18.6601, "lon": 12.756167}, {"type": "node", "id": 419495795, "lat": 18.659217, "lon": 12.753683}, {"type": "node", "id": 419495796, "lat": 18.65875, "lon": 12.752617}, {"type": "node", "id": 419495797, "lat": 18.65765, "lon": 12.750617}, {"type": "node", "id": 419495798, "lat": 18.657133, "lon": 12.749533}, {"type": "node", "id": 419495799, "lat": 18.656217, "lon": 12.747483}, {"type": "node", "id": 419495800, "lat": 18.65585, "lon": 12.746383}, {"type": "node", "id": 419495801, "lat": 18.655417, "lon": 12.745283}, {"type": "node", "id": 419495802, "lat": 18.654917, "lon": 12.74435}, {"type": "node", "id": 419495803, "lat": 18.653683, "lon": 12.742667}, {"type": "node", "id": 419495804, "lat": 18.652683, "lon": 12.740817}, {"type": "node", "id": 419495805, "lat": 18.651417, "lon": 12.737683}, {"type": "node", "id": 419495806, "lat": 18.650933, "lon": 12.736667}, {"type": "node", "id": 419495807, "lat": 18.650383, "lon": 12.735783}, {"type": "node", "id": 419495808, "lat": 18.649917, "lon": 12.734783}, {"type": "node", "id": 419495809, "lat": 18.6476, "lon": 12.729283}, {"type": "node", "id": 419495810, "lat": 18.6469, "lon": 12.726967}, {"type": "node", "id": 419495811, "lat": 18.6464993, "lon": 12.7259405}, {"type": "node", "id": 419495812, "lat": 18.6461791, "lon": 12.7259016}, {"type": "node", "id": 419495813, "lat": 18.6453754, "lon": 12.7262831}, {"type": "node", "id": 419495814, "lat": 18.6447559, "lon": 12.7264997}, {"type": "node", "id": 419495815, "lat": 18.6444204, "lon": 12.7261806}, {"type": "node", "id": 419495816, "lat": 18.6442425, "lon": 12.7257997}, {"type": "node", "id": 419495817, "lat": 18.6435, "lon": 12.724083}, {"type": "node", "id": 419495818, "lat": 18.642583, "lon": 12.721783}, {"type": "node", "id": 419495819, "lat": 18.6408, "lon": 12.71625}, {"type": "node", "id": 419495820, "lat": 18.6385, "lon": 12.710017}, {"type": "node", "id": 419495821, "lat": 18.637467, "lon": 12.706517}, {"type": "node", "id": 419495822, "lat": 18.6362, "lon": 12.703067}, {"type": "node", "id": 419495823, "lat": 18.633267, "lon": 12.693117}, {"type": "node", "id": 419495824, "lat": 18.632367, "lon": 12.6897}, {"type": "node", "id": 419495825, "lat": 18.631733, "lon": 12.68785}, {"type": "node", "id": 419495826, "lat": 18.630383, "lon": 12.684317}, {"type": "node", "id": 419495827, "lat": 18.629217, "lon": 12.68065}, {"type": "node", "id": 419495828, "lat": 18.6287, "lon": 12.6788}, {"type": "node", "id": 419495829, "lat": 18.626933, "lon": 12.673083}, {"type": "node", "id": 419495830, "lat": 18.626267, "lon": 12.671217}, {"type": "node", "id": 419495831, "lat": 18.62555, "lon": 12.669467}, {"type": "node", "id": 419495832, "lat": 18.624483, "lon": 12.6666}, {"type": "node", "id": 419495833, "lat": 18.6242, "lon": 12.664983}, {"type": "node", "id": 419495834, "lat": 18.62405, "lon": 12.66335}, {"type": "node", "id": 419495835, "lat": 18.623833, "lon": 12.66165}, {"type": "node", "id": 419495836, "lat": 18.623367, "lon": 12.659867}, {"type": "node", "id": 419495837, "lat": 18.622817, "lon": 12.658083}, {"type": "node", "id": 419495838, "lat": 18.6216, "lon": 12.654517}, {"type": "node", "id": 419495839, "lat": 18.62125, "lon": 12.652717}, {"type": "node", "id": 419495840, "lat": 18.620133, "lon": 12.647583}, {"type": "node", "id": 419495841, "lat": 18.620117, "lon": 12.646033}, {"type": "node", "id": 419495842, "lat": 18.619917, "lon": 12.6446}, {"type": "node", "id": 419495843, "lat": 18.6191, "lon": 12.641183}, {"type": "node", "id": 419495844, "lat": 18.61855, "lon": 12.639483}, {"type": "node", "id": 419495845, "lat": 18.61435, "lon": 12.628433}, {"type": "node", "id": 419495846, "lat": 18.613083, "lon": 12.624917}, {"type": "node", "id": 419495847, "lat": 18.61095, "lon": 12.61945}, {"type": "node", "id": 419495848, "lat": 18.609433, "lon": 12.6151}, {"type": "node", "id": 419495849, "lat": 18.608133, "lon": 12.611583}, {"type": "node", "id": 419495850, "lat": 18.606617, "lon": 12.60765}, {"type": "node", "id": 419495851, "lat": 18.604917, "lon": 12.604217}, {"type": "node", "id": 419495852, "lat": 18.602933, "lon": 12.60075}, {"type": "node", "id": 419495853, "lat": 18.602, "lon": 12.599}, {"type": "node", "id": 419495854, "lat": 18.600717, "lon": 12.5971}, {"type": "node", "id": 419495855, "lat": 18.59935, "lon": 12.595433}, {"type": "node", "id": 419495856, "lat": 18.598117, "lon": 12.593417}, {"type": "node", "id": 419495857, "lat": 18.597233, "lon": 12.591217}, {"type": "node", "id": 419495858, "lat": 18.5958, "lon": 12.587083}, {"type": "node", "id": 419495859, "lat": 18.594883, "lon": 12.585333}, {"type": "node", "id": 419495860, "lat": 18.594733, "lon": 12.583383}, {"type": "node", "id": 419495861, "lat": 18.594317, "lon": 12.581633}, {"type": "node", "id": 419495862, "lat": 18.593617, "lon": 12.579783}, {"type": "node", "id": 419495863, "lat": 18.591917, "lon": 12.576}, {"type": "node", "id": 419495864, "lat": 18.591133, "lon": 12.574033}, {"type": "node", "id": 419495865, "lat": 18.590433, "lon": 12.57205}, {"type": "node", "id": 419495866, "lat": 18.589183, "lon": 12.568033}, {"type": "node", "id": 419495867, "lat": 18.588483, "lon": 12.565933}, {"type": "node", "id": 419495868, "lat": 18.586783, "lon": 12.560983}, {"type": "node", "id": 419495869, "lat": 18.585433, "lon": 12.553133}, {"type": "node", "id": 419495870, "lat": 18.584933, "lon": 12.55055}, {"type": "node", "id": 419495871, "lat": 18.583717, "lon": 12.54495}, {"type": "node", "id": 419495872, "lat": 18.583367, "lon": 12.54275}, {"type": "node", "id": 419495873, "lat": 18.582967, "lon": 12.540683}, {"type": "node", "id": 419495874, "lat": 18.582667, "lon": 12.5385}, {"type": "node", "id": 419495875, "lat": 18.582183, "lon": 12.536383}, {"type": "node", "id": 419495876, "lat": 18.581367, "lon": 12.532367}, {"type": "node", "id": 419495877, "lat": 18.5809, "lon": 12.528917}, {"type": "node", "id": 419495887, "lat": 18.581733, "lon": 12.524267}, {"type": "node", "id": 419495888, "lat": 18.5817, "lon": 12.522917}, {"type": "node", "id": 419495889, "lat": 18.581417, "lon": 12.521783}, {"type": "node", "id": 419495890, "lat": 18.58135, "lon": 12.521217}, {"type": "node", "id": 419495891, "lat": 18.581367, "lon": 12.52115}, {"type": "node", "id": 419495892, "lat": 18.581783, "lon": 12.520733}, {"type": "node", "id": 419495893, "lat": 18.5821, "lon": 12.519917}, {"type": "node", "id": 419495894, "lat": 18.581967, "lon": 12.51855}, {"type": "node", "id": 419495895, "lat": 18.581683, "lon": 12.51685}, {"type": "node", "id": 419495896, "lat": 18.5811, "lon": 12.513983}, {"type": "node", "id": 419495897, "lat": 18.5809, "lon": 12.512717}, {"type": "node", "id": 419495898, "lat": 18.5808, "lon": 12.51165}, {"type": "node", "id": 419495899, "lat": 18.580367, "lon": 12.510017}, {"type": "node", "id": 419495900, "lat": 18.5796, "lon": 12.508183}, {"type": "node", "id": 419495901, "lat": 18.578517, "lon": 12.50425}, {"type": "node", "id": 419495902, "lat": 18.57815, "lon": 12.502267}, {"type": "node", "id": 419495903, "lat": 18.578083, "lon": 12.500233}, {"type": "node", "id": 419495904, "lat": 18.577867, "lon": 12.498117}, {"type": "node", "id": 419495905, "lat": 18.577483, "lon": 12.496083}, {"type": "node", "id": 419495906, "lat": 18.577133, "lon": 12.4945}, {"type": "node", "id": 419495907, "lat": 18.5771, "lon": 12.493167}, {"type": "node", "id": 419495908, "lat": 18.576867, "lon": 12.491817}, {"type": "node", "id": 419495909, "lat": 18.576617, "lon": 12.488667}, {"type": "node", "id": 419495910, "lat": 18.5761, "lon": 12.484867}, {"type": "node", "id": 419495911, "lat": 18.5752, "lon": 12.481267}, {"type": "node", "id": 419495912, "lat": 18.574983, "lon": 12.479533}, {"type": "node", "id": 419495913, "lat": 18.574933, "lon": 12.478567}, {"type": "node", "id": 419495914, "lat": 18.574833, "lon": 12.477683}, {"type": "node", "id": 419495915, "lat": 18.574417, "lon": 12.4753}, {"type": "node", "id": 419495916, "lat": 18.5738, "lon": 12.472833}, {"type": "node", "id": 419495917, "lat": 18.573217, "lon": 12.470233}, {"type": "node", "id": 419495918, "lat": 18.573, "lon": 12.468933}, {"type": "node", "id": 419495919, "lat": 18.57235, "lon": 12.4664}, {"type": "node", "id": 419495920, "lat": 18.5720363, "lon": 12.4644898}, {"type": "node", "id": 419495921, "lat": 18.5719552, "lon": 12.4624196}, {"type": "node", "id": 419495922, "lat": 18.5719048, "lon": 12.4600369}, {"type": "node", "id": 419495929, "lat": 18.5714209, "lon": 12.4580632}, {"type": "node", "id": 419495930, "lat": 18.571133, "lon": 12.45715}, {"type": "node", "id": 419495931, "lat": 18.57075, "lon": 12.455033}, {"type": "node", "id": 419495932, "lat": 18.57045, "lon": 12.453867}, {"type": "node", "id": 419495933, "lat": 18.570017, "lon": 12.45265}, {"type": "node", "id": 419495934, "lat": 18.569267, "lon": 12.45025}, {"type": "node", "id": 419495935, "lat": 18.56905, "lon": 12.449083}, {"type": "node", "id": 419495936, "lat": 18.567433, "lon": 12.444367}, {"type": "node", "id": 419495937, "lat": 18.566, "lon": 12.44085}, {"type": "node", "id": 419495938, "lat": 18.5656, "lon": 12.4396}, {"type": "node", "id": 419495939, "lat": 18.565, "lon": 12.437217}, {"type": "node", "id": 419495940, "lat": 18.5642, "lon": 12.434767}, {"type": "node", "id": 419495941, "lat": 18.563183, "lon": 12.431083}, {"type": "node", "id": 419495942, "lat": 18.562717, "lon": 12.429783}, {"type": "node", "id": 419495943, "lat": 18.562117, "lon": 12.4283}, {"type": "node", "id": 419495944, "lat": 18.56085, "lon": 12.42425}, {"type": "node", "id": 419495945, "lat": 18.560583, "lon": 12.422767}, {"type": "node", "id": 419495946, "lat": 18.558733, "lon": 12.41455}, {"type": "node", "id": 419495947, "lat": 18.5589, "lon": 12.412917}, {"type": "node", "id": 419495948, "lat": 18.559117, "lon": 12.41185}, {"type": "node", "id": 419495949, "lat": 18.559033, "lon": 12.41165}, {"type": "node", "id": 419495950, "lat": 18.558567, "lon": 12.410933}, {"type": "node", "id": 419495951, "lat": 18.557533, "lon": 12.40815}, {"type": "node", "id": 419495952, "lat": 18.557, "lon": 12.4065}, {"type": "node", "id": 419495953, "lat": 18.55625, "lon": 12.4049}, {"type": "node", "id": 419495954, "lat": 18.555283, "lon": 12.4038}, {"type": "node", "id": 419495955, "lat": 18.554783, "lon": 12.402267}, {"type": "node", "id": 419495956, "lat": 18.55415, "lon": 12.4001}, {"type": "node", "id": 419495957, "lat": 18.553583, "lon": 12.398433}, {"type": "node", "id": 419495958, "lat": 18.551433, "lon": 12.39075}, {"type": "node", "id": 419495959, "lat": 18.550583, "lon": 12.38905}, {"type": "node", "id": 419495961, "lat": 18.54985, "lon": 12.387333}, {"type": "node", "id": 419495962, "lat": 18.54925, "lon": 12.38555}, {"type": "node", "id": 419495963, "lat": 18.548533, "lon": 12.383667}, {"type": "node", "id": 419495965, "lat": 18.547433, "lon": 12.37975}, {"type": "node", "id": 419495967, "lat": 18.5462, "lon": 12.376167}, {"type": "node", "id": 419495970, "lat": 18.545733, "lon": 12.374433}, {"type": "node", "id": 419495972, "lat": 18.545217, "lon": 12.372867}, {"type": "node", "id": 419495974, "lat": 18.54395, "lon": 12.369533}, {"type": "node", "id": 419495976, "lat": 18.543567, "lon": 12.367967}, {"type": "node", "id": 419495978, "lat": 18.54295, "lon": 12.3663}, {"type": "node", "id": 419495980, "lat": 18.54225, "lon": 12.364767}, {"type": "node", "id": 419495982, "lat": 18.54195, "lon": 12.36355}, {"type": "node", "id": 419495984, "lat": 18.541783, "lon": 12.362217}, {"type": "node", "id": 419495986, "lat": 18.5406, "lon": 12.3603}, {"type": "node", "id": 419495988, "lat": 18.539833, "lon": 12.357933}, {"type": "node", "id": 419495990, "lat": 18.539083, "lon": 12.35395}, {"type": "node", "id": 419495992, "lat": 18.538683, "lon": 12.3525}, {"type": "node", "id": 419495994, "lat": 18.537967, "lon": 12.349283}, {"type": "node", "id": 419495996, "lat": 18.537783, "lon": 12.34805}, {"type": "node", "id": 419495998, "lat": 18.537433, "lon": 12.348383}, {"type": "node", "id": 419496000, "lat": 18.5373, "lon": 12.349417}, {"type": "node", "id": 419496002, "lat": 18.53675, "lon": 12.35025}, {"type": "node", "id": 419496005, "lat": 18.5365, "lon": 12.3504}, {"type": "node", "id": 419496006, "lat": 18.535933, "lon": 12.350917}, {"type": "node", "id": 419496015, "lat": 18.535483, "lon": 12.35125}, {"type": "node", "id": 419496017, "lat": 18.5348, "lon": 12.3516}, {"type": "node", "id": 419496019, "lat": 18.534067, "lon": 12.35315}, {"type": "node", "id": 419496021, "lat": 18.533917, "lon": 12.354233}, {"type": "node", "id": 419496022, "lat": 18.534117, "lon": 12.355117}, {"type": "node", "id": 419496024, "lat": 18.534183, "lon": 12.3561}, {"type": "node", "id": 419496026, "lat": 18.533533, "lon": 12.3563}, {"type": "node", "id": 419496028, "lat": 18.532933, "lon": 12.355933}, {"type": "node", "id": 419496031, "lat": 18.5323, "lon": 12.3557}, {"type": "node", "id": 419496033, "lat": 18.531117, "lon": 12.355817}, {"type": "node", "id": 419496035, "lat": 18.53055, "lon": 12.356667}, {"type": "node", "id": 419496037, "lat": 18.530733, "lon": 12.3581}, {"type": "node", "id": 419496039, "lat": 18.53145, "lon": 12.361633}, {"type": "node", "id": 419496041, "lat": 18.532417, "lon": 12.367183}, {"type": "node", "id": 419496043, "lat": 18.532683, "lon": 12.3692}, {"type": "node", "id": 419496045, "lat": 18.532583, "lon": 12.371233}, {"type": "node", "id": 419496047, "lat": 18.532217, "lon": 12.372967}, {"type": "node", "id": 419496049, "lat": 18.531833, "lon": 12.376467}, {"type": "node", "id": 419496051, "lat": 18.531017, "lon": 12.37975}, {"type": "node", "id": 419496053, "lat": 18.53035, "lon": 12.380617}, {"type": "node", "id": 419496055, "lat": 18.529783, "lon": 12.3801}, {"type": "node", "id": 419496057, "lat": 18.529433, "lon": 12.379667}, {"type": "node", "id": 419496059, "lat": 18.528517, "lon": 12.3797}, {"type": "node", "id": 419496061, "lat": 18.527567, "lon": 12.380733}, {"type": "node", "id": 419496063, "lat": 18.527, "lon": 12.38185}, {"type": "node", "id": 419496071, "lat": 18.526733, "lon": 12.381983}, {"type": "node", "id": 419496074, "lat": 18.526, "lon": 12.381317}, {"type": "node", "id": 419496076, "lat": 18.52525, "lon": 12.379333}, {"type": "node", "id": 419496077, "lat": 18.524683, "lon": 12.37835}, {"type": "node", "id": 419496078, "lat": 18.523183, "lon": 12.375983}, {"type": "node", "id": 419496079, "lat": 18.522433, "lon": 12.374617}, {"type": "node", "id": 419496080, "lat": 18.522217, "lon": 12.37405}, {"type": "node", "id": 419496081, "lat": 18.52155, "lon": 12.37325}, {"type": "node", "id": 419496082, "lat": 18.520633, "lon": 12.371}, {"type": "node", "id": 419496083, "lat": 18.519917, "lon": 12.368917}, {"type": "node", "id": 419496084, "lat": 18.5182, "lon": 12.36455}, {"type": "node", "id": 419496085, "lat": 18.5168, "lon": 12.36145}, {"type": "node", "id": 419496087, "lat": 18.5128, "lon": 12.352317}, {"type": "node", "id": 419496089, "lat": 18.510883, "lon": 12.346883}, {"type": "node", "id": 419496091, "lat": 18.50945, "lon": 12.343483}, {"type": "node", "id": 419496093, "lat": 18.508617, "lon": 12.341633}, {"type": "node", "id": 419496095, "lat": 18.50775, "lon": 12.339867}, {"type": "node", "id": 419496097, "lat": 18.506583, "lon": 12.338117}, {"type": "node", "id": 419496099, "lat": 18.504183, "lon": 12.335233}, {"type": "node", "id": 419496101, "lat": 18.503333, "lon": 12.334083}, {"type": "node", "id": 419496103, "lat": 18.50245, "lon": 12.332783}, {"type": "node", "id": 419496105, "lat": 18.500633, "lon": 12.32955}, {"type": "node", "id": 419496107, "lat": 18.4999, "lon": 12.328}, {"type": "node", "id": 419496109, "lat": 18.49915, "lon": 12.326667}, {"type": "node", "id": 419496111, "lat": 18.497733, "lon": 12.324317}, {"type": "node", "id": 419496113, "lat": 18.496733, "lon": 12.322917}, {"type": "node", "id": 419496117, "lat": 18.495983, "lon": 12.321733}, {"type": "node", "id": 419496118, "lat": 18.495483, "lon": 12.320233}, {"type": "node", "id": 419496119, "lat": 18.495, "lon": 12.318167}, {"type": "node", "id": 419496120, "lat": 18.494283, "lon": 12.315767}, {"type": "node", "id": 419496121, "lat": 18.4933, "lon": 12.313467}, {"type": "node", "id": 419496122, "lat": 18.4905, "lon": 12.308017}, {"type": "node", "id": 419496123, "lat": 18.489867, "lon": 12.306417}, {"type": "node", "id": 419496124, "lat": 18.489, "lon": 12.304767}, {"type": "node", "id": 419496125, "lat": 18.4878, "lon": 12.302667}, {"type": "node", "id": 419496126, "lat": 18.486767, "lon": 12.30075}, {"type": "node", "id": 419496127, "lat": 18.485533, "lon": 12.2978}, {"type": "node", "id": 419496128, "lat": 18.484933, "lon": 12.29605}, {"type": "node", "id": 419496129, "lat": 18.484417, "lon": 12.294317}, {"type": "node", "id": 419496130, "lat": 18.4838, "lon": 12.293}, {"type": "node", "id": 419496131, "lat": 18.482967, "lon": 12.292033}, {"type": "node", "id": 419496132, "lat": 18.48205, "lon": 12.29065}, {"type": "node", "id": 419496133, "lat": 18.4815, "lon": 12.2893}, {"type": "node", "id": 419496134, "lat": 18.480883, "lon": 12.287533}, {"type": "node", "id": 419496135, "lat": 18.480517, "lon": 12.285567}, {"type": "node", "id": 419496136, "lat": 18.47945, "lon": 12.281417}, {"type": "node", "id": 419496137, "lat": 18.479033, "lon": 12.27915}, {"type": "node", "id": 419496138, "lat": 18.478367, "lon": 12.275967}, {"type": "node", "id": 419496139, "lat": 18.47795, "lon": 12.273633}, {"type": "node", "id": 419496140, "lat": 18.477433, "lon": 12.271317}, {"type": "node", "id": 419496141, "lat": 18.476183, "lon": 12.264283}, {"type": "node", "id": 419496142, "lat": 18.4758, "lon": 12.2625}, {"type": "node", "id": 419496143, "lat": 18.474933, "lon": 12.2593}, {"type": "node", "id": 419496144, "lat": 18.474517, "lon": 12.2576}, {"type": "node", "id": 419496145, "lat": 18.4742, "lon": 12.2559}, {"type": "node", "id": 419496146, "lat": 18.473833, "lon": 12.254317}, {"type": "node", "id": 419496147, "lat": 18.472717, "lon": 12.251067}, {"type": "node", "id": 419496148, "lat": 18.472267, "lon": 12.249483}, {"type": "node", "id": 419496149, "lat": 18.47125, "lon": 12.246367}, {"type": "node", "id": 419496150, "lat": 18.4692, "lon": 12.2395}, {"type": "node", "id": 419496151, "lat": 18.468467, "lon": 12.237667}, {"type": "node", "id": 419496152, "lat": 18.467933, "lon": 12.235917}, {"type": "node", "id": 419496153, "lat": 18.46715, "lon": 12.232267}, {"type": "node", "id": 419496154, "lat": 18.466633, "lon": 12.230483}, {"type": "node", "id": 419496155, "lat": 18.466283, "lon": 12.22895}, {"type": "node", "id": 419496156, "lat": 18.466067, "lon": 12.2274}, {"type": "node", "id": 419496157, "lat": 18.465683, "lon": 12.226}, {"type": "node", "id": 419496158, "lat": 18.4649, "lon": 12.22485}, {"type": "node", "id": 419496159, "lat": 18.464267, "lon": 12.222983}, {"type": "node", "id": 419496160, "lat": 18.46355, "lon": 12.219483}, {"type": "node", "id": 419496161, "lat": 18.462317, "lon": 12.21195}, {"type": "node", "id": 419496162, "lat": 18.462, "lon": 12.210333}, {"type": "node", "id": 419496163, "lat": 18.46145, "lon": 12.208717}, {"type": "node", "id": 419496164, "lat": 18.46115, "lon": 12.207617}, {"type": "node", "id": 419496165, "lat": 18.4604, "lon": 12.206917}, {"type": "node", "id": 419496166, "lat": 18.4598, "lon": 12.205133}, {"type": "node", "id": 419496167, "lat": 18.459567, "lon": 12.203233}, {"type": "node", "id": 419496168, "lat": 18.459017, "lon": 12.201333}, {"type": "node", "id": 419496169, "lat": 18.45835, "lon": 12.199817}, {"type": "node", "id": 419496170, "lat": 18.457483, "lon": 12.198}, {"type": "node", "id": 419496171, "lat": 18.45695, "lon": 12.196233}, {"type": "node", "id": 419496172, "lat": 18.456717, "lon": 12.194683}, {"type": "node", "id": 419496173, "lat": 18.45635, "lon": 12.19285}, {"type": "node", "id": 419496174, "lat": 18.455533, "lon": 12.19115}, {"type": "node", "id": 419496175, "lat": 18.4542, "lon": 12.18955}, {"type": "node", "id": 419496176, "lat": 18.453133, "lon": 12.187717}, {"type": "node", "id": 419496177, "lat": 18.452833, "lon": 12.185767}, {"type": "node", "id": 419496178, "lat": 18.451783, "lon": 12.181883}, {"type": "node", "id": 419496179, "lat": 18.45145, "lon": 12.179867}, {"type": "node", "id": 419496180, "lat": 18.450533, "lon": 12.176367}, {"type": "node", "id": 419496181, "lat": 18.449833, "lon": 12.173417}, {"type": "node", "id": 419496182, "lat": 18.449417, "lon": 12.171867}, {"type": "node", "id": 419496183, "lat": 18.44875, "lon": 12.170317}, {"type": "node", "id": 419496184, "lat": 18.4485, "lon": 12.168717}, {"type": "node", "id": 419496185, "lat": 18.448383, "lon": 12.167067}, {"type": "node", "id": 419496186, "lat": 18.4479, "lon": 12.165217}, {"type": "node", "id": 419496187, "lat": 18.447483, "lon": 12.16325}, {"type": "node", "id": 419496188, "lat": 18.447083, "lon": 12.16125}, {"type": "node", "id": 419496189, "lat": 18.446767, "lon": 12.159167}, {"type": "node", "id": 419496190, "lat": 18.44615, "lon": 12.157067}, {"type": "node", "id": 419496191, "lat": 18.445467, "lon": 12.155133}, {"type": "node", "id": 419496192, "lat": 18.444883, "lon": 12.153083}, {"type": "node", "id": 419496193, "lat": 18.443333, "lon": 12.146717}, {"type": "node", "id": 419496194, "lat": 18.44225, "lon": 12.142617}, {"type": "node", "id": 419496195, "lat": 18.4418, "lon": 12.1406}, {"type": "node", "id": 419496196, "lat": 18.44125, "lon": 12.136333}, {"type": "node", "id": 419496197, "lat": 18.441017, "lon": 12.134183}, {"type": "node", "id": 419496198, "lat": 18.441, "lon": 12.132}, {"type": "node", "id": 419496199, "lat": 18.440833, "lon": 12.127917}, {"type": "node", "id": 419496200, "lat": 18.440567, "lon": 12.125}, {"type": "node", "id": 419496201, "lat": 18.440067, "lon": 12.124267}, {"type": "node", "id": 419496202, "lat": 18.439967, "lon": 12.124033}, {"type": "node", "id": 419496203, "lat": 18.4402, "lon": 12.123867}, {"type": "node", "id": 419496204, "lat": 18.44005, "lon": 12.134633}, {"type": "node", "id": 419496205, "lat": 18.439483, "lon": 12.134417}, {"type": "node", "id": 419496206, "lat": 18.4377, "lon": 12.132817}, {"type": "node", "id": 419496207, "lat": 18.435983, "lon": 12.130933}, {"type": "node", "id": 419496208, "lat": 18.4352, "lon": 12.129517}, {"type": "node", "id": 419496209, "lat": 18.434033, "lon": 12.126}, {"type": "node", "id": 419496210, "lat": 18.433317, "lon": 12.122783}, {"type": "node", "id": 419496211, "lat": 18.43265, "lon": 12.119217}, {"type": "node", "id": 419496212, "lat": 18.432217, "lon": 12.117383}, {"type": "node", "id": 419496213, "lat": 18.4316, "lon": 12.1156}, {"type": "node", "id": 419496214, "lat": 18.430333, "lon": 12.112467}, {"type": "node", "id": 419496215, "lat": 18.42995, "lon": 12.110667}, {"type": "node", "id": 419496216, "lat": 18.429467, "lon": 12.109233}, {"type": "node", "id": 419496217, "lat": 18.42845, "lon": 12.107767}, {"type": "node", "id": 419496218, "lat": 18.42805, "lon": 12.106667}, {"type": "node", "id": 419496219, "lat": 18.427133, "lon": 12.105483}, {"type": "node", "id": 419496220, "lat": 18.4267, "lon": 12.103883}, {"type": "node", "id": 419496221, "lat": 18.426617, "lon": 12.0996}, {"type": "node", "id": 419496222, "lat": 18.426783, "lon": 12.092967}, {"type": "node", "id": 419496223, "lat": 18.426383, "lon": 12.0916}, {"type": "node", "id": 419496224, "lat": 18.425083, "lon": 12.0905}, {"type": "node", "id": 419496225, "lat": 18.42385, "lon": 12.0888}, {"type": "node", "id": 419496226, "lat": 18.4231, "lon": 12.0867}, {"type": "node", "id": 419496227, "lat": 18.42225, "lon": 12.084633}, {"type": "node", "id": 419496228, "lat": 18.421967, "lon": 12.082483}, {"type": "node", "id": 419496229, "lat": 18.421517, "lon": 12.080417}, {"type": "node", "id": 419496230, "lat": 18.421133, "lon": 12.078317}, {"type": "node", "id": 419496231, "lat": 18.420883, "lon": 12.07625}, {"type": "node", "id": 419496232, "lat": 18.420733, "lon": 12.074217}, {"type": "node", "id": 419496233, "lat": 18.420467, "lon": 12.07215}, {"type": "node", "id": 419496234, "lat": 18.42025, "lon": 12.070033}, {"type": "node", "id": 419496235, "lat": 18.419917, "lon": 12.067783}, {"type": "node", "id": 419496236, "lat": 18.419367, "lon": 12.063467}, {"type": "node", "id": 419496237, "lat": 18.419017, "lon": 12.061333}, {"type": "node", "id": 419496238, "lat": 18.418483, "lon": 12.059133}, {"type": "node", "id": 419496239, "lat": 18.417133, "lon": 12.052933}, {"type": "node", "id": 419496240, "lat": 18.4157, "lon": 12.04455}, {"type": "node", "id": 419496241, "lat": 18.41375, "lon": 12.034233}, {"type": "node", "id": 419496242, "lat": 18.412817, "lon": 12.0295}, {"type": "node", "id": 419496243, "lat": 18.4119, "lon": 12.025167}, {"type": "node", "id": 419496244, "lat": 18.411067, "lon": 12.020583}, {"type": "node", "id": 419496245, "lat": 18.41075, "lon": 12.01835}, {"type": "node", "id": 419496246, "lat": 18.410383, "lon": 12.013917}, {"type": "node", "id": 419496247, "lat": 18.409817, "lon": 12.009667}, {"type": "node", "id": 419496248, "lat": 18.409117, "lon": 12.0056}, {"type": "node", "id": 419496249, "lat": 18.408867, "lon": 12.003483}, {"type": "node", "id": 419496250, "lat": 18.408467, "lon": 11.999217}, {"type": "node", "id": 419496251, "lat": 18.408367, "lon": 11.997133}, {"type": "node", "id": 419496252, "lat": 18.4076, "lon": 11.995283}, {"type": "node", "id": 419496253, "lat": 18.4069, "lon": 11.993433}, {"type": "node", "id": 419496254, "lat": 18.405567, "lon": 11.9893}, {"type": "node", "id": 419496255, "lat": 18.404967, "lon": 11.987267}, {"type": "node", "id": 419496256, "lat": 18.403917, "lon": 11.982883}, {"type": "node", "id": 419496257, "lat": 18.403433, "lon": 11.980683}, {"type": "node", "id": 419496258, "lat": 18.401317, "lon": 11.972267}, {"type": "node", "id": 419496259, "lat": 18.40085, "lon": 11.9702}, {"type": "node", "id": 419496260, "lat": 18.40005, "lon": 11.96615}, {"type": "node", "id": 419496261, "lat": 18.399167, "lon": 11.962067}, {"type": "node", "id": 419496262, "lat": 18.398783, "lon": 11.959867}, {"type": "node", "id": 419496263, "lat": 18.397433, "lon": 11.95125}, {"type": "node", "id": 419496264, "lat": 18.396817, "lon": 11.947967}, {"type": "node", "id": 419496265, "lat": 18.396467, "lon": 11.945583}, {"type": "node", "id": 419496266, "lat": 18.39555, "lon": 11.940183}, {"type": "node", "id": 419496267, "lat": 18.395317, "lon": 11.938317}, {"type": "node", "id": 419496268, "lat": 18.395, "lon": 11.9365}, {"type": "node", "id": 419496269, "lat": 18.394817, "lon": 11.934517}, {"type": "node", "id": 419496270, "lat": 18.39455, "lon": 11.932383}, {"type": "node", "id": 419496271, "lat": 18.393133, "lon": 11.923517}, {"type": "node", "id": 419496272, "lat": 18.391283, "lon": 11.910067}, {"type": "node", "id": 419496273, "lat": 18.39045, "lon": 11.90575}, {"type": "node", "id": 419496274, "lat": 18.3901, "lon": 11.903617}, {"type": "node", "id": 419496275, "lat": 18.389833, "lon": 11.901467}, {"type": "node", "id": 419496276, "lat": 18.388833, "lon": 11.894883}, {"type": "node", "id": 419496277, "lat": 18.3876, "lon": 11.888883}, {"type": "node", "id": 419496278, "lat": 18.387133, "lon": 11.8873}, {"type": "node", "id": 419496279, "lat": 18.385667, "lon": 11.884033}, {"type": "node", "id": 419496280, "lat": 18.384833, "lon": 11.882433}, {"type": "node", "id": 419496281, "lat": 18.383933, "lon": 11.880933}, {"type": "node", "id": 419496282, "lat": 18.38305, "lon": 11.879317}, {"type": "node", "id": 419496283, "lat": 18.3806, "lon": 11.873517}, {"type": "node", "id": 419496284, "lat": 18.379633, "lon": 11.871517}, {"type": "node", "id": 419496285, "lat": 18.377567, "lon": 11.867617}, {"type": "node", "id": 419496286, "lat": 18.374933, "lon": 11.863133}, {"type": "node", "id": 419496287, "lat": 18.373833, "lon": 11.861183}, {"type": "node", "id": 419496288, "lat": 18.372017, "lon": 11.85705}, {"type": "node", "id": 419496289, "lat": 18.370833, "lon": 11.8542}, {"type": "node", "id": 419496290, "lat": 18.369167, "lon": 11.849933}, {"type": "node", "id": 419496291, "lat": 18.368267, "lon": 11.847817}, {"type": "node", "id": 419496292, "lat": 18.367267, "lon": 11.8457}, {"type": "node", "id": 419496293, "lat": 18.366183, "lon": 11.84365}, {"type": "node", "id": 419496294, "lat": 18.365267, "lon": 11.841567}, {"type": "node", "id": 419496295, "lat": 18.36435, "lon": 11.839367}, {"type": "node", "id": 419496296, "lat": 18.362683, "lon": 11.835117}, {"type": "node", "id": 419496297, "lat": 18.36225, "lon": 11.833083}, {"type": "node", "id": 419496298, "lat": 18.361583, "lon": 11.831333}, {"type": "node", "id": 419496299, "lat": 18.360017, "lon": 11.82805}, {"type": "node", "id": 419496300, "lat": 18.358033, "lon": 11.824483}, {"type": "node", "id": 419496301, "lat": 18.357383, "lon": 11.822383}, {"type": "node", "id": 419496302, "lat": 18.356583, "lon": 11.820283}, {"type": "node", "id": 419496303, "lat": 18.355, "lon": 11.813317}, {"type": "node", "id": 419496304, "lat": 18.354417, "lon": 11.81125}, {"type": "node", "id": 419496305, "lat": 18.35305, "lon": 11.807067}, {"type": "node", "id": 419496306, "lat": 18.352067, "lon": 11.8048}, {"type": "node", "id": 419496307, "lat": 18.350733, "lon": 11.802583}, {"type": "node", "id": 419496308, "lat": 18.349367, "lon": 11.80055}, {"type": "node", "id": 419496309, "lat": 18.347233, "lon": 11.79795}, {"type": "node", "id": 419496310, "lat": 18.345, "lon": 11.794967}, {"type": "node", "id": 419496311, "lat": 18.344083, "lon": 11.7932}, {"type": "node", "id": 419496312, "lat": 18.343367, "lon": 11.791317}, {"type": "node", "id": 419496313, "lat": 18.342767, "lon": 11.789383}, {"type": "node", "id": 419496314, "lat": 18.342067, "lon": 11.787533}, {"type": "node", "id": 419496315, "lat": 18.34065, "lon": 11.783933}, {"type": "node", "id": 419496316, "lat": 18.339867, "lon": 11.7822}, {"type": "node", "id": 419496317, "lat": 18.338633, "lon": 11.781283}, {"type": "node", "id": 419496318, "lat": 18.33785, "lon": 11.78185}, {"type": "node", "id": 419496319, "lat": 18.337483, "lon": 11.78345}, {"type": "node", "id": 419496320, "lat": 18.337033, "lon": 11.7862}, {"type": "node", "id": 419496321, "lat": 18.336833, "lon": 11.787683}, {"type": "node", "id": 419496322, "lat": 18.33675, "lon": 11.789317}, {"type": "node", "id": 419496323, "lat": 18.336633, "lon": 11.79475}, {"type": "node", "id": 419496324, "lat": 18.336467, "lon": 11.798317}, {"type": "node", "id": 419496325, "lat": 18.336333, "lon": 11.8002}, {"type": "node", "id": 419496326, "lat": 18.336383, "lon": 11.80195}, {"type": "node", "id": 419496327, "lat": 18.336533, "lon": 11.803783}, {"type": "node", "id": 419496328, "lat": 18.336517, "lon": 11.8054}, {"type": "node", "id": 419496329, "lat": 18.336283, "lon": 11.807017}, {"type": "node", "id": 419496330, "lat": 18.3353065, "lon": 11.8073102}, {"type": "node", "id": 419496331, "lat": 18.335067, "lon": 11.80725}, {"type": "node", "id": 419496333, "lat": 18.334533, "lon": 11.806767}, {"type": "node", "id": 419496334, "lat": 18.33365, "lon": 11.805633}, {"type": "node", "id": 419496335, "lat": 18.332433, "lon": 11.804183}, {"type": "node", "id": 419496336, "lat": 18.3305, "lon": 11.801917}, {"type": "node", "id": 419496337, "lat": 18.3288, "lon": 11.80035}, {"type": "node", "id": 419496338, "lat": 18.327517, "lon": 11.799167}, {"type": "node", "id": 419496339, "lat": 18.326533, "lon": 11.797783}, {"type": "node", "id": 419496340, "lat": 18.325867, "lon": 11.796083}, {"type": "node", "id": 419496341, "lat": 18.32535, "lon": 11.794167}, {"type": "node", "id": 419496342, "lat": 18.324683, "lon": 11.7916}, {"type": "node", "id": 419496343, "lat": 18.323983, "lon": 11.78835}, {"type": "node", "id": 419496344, "lat": 18.3236, "lon": 11.786017}, {"type": "node", "id": 419496345, "lat": 18.323167, "lon": 11.783633}, {"type": "node", "id": 419496346, "lat": 18.322683, "lon": 11.781317}, {"type": "node", "id": 419496347, "lat": 18.322367, "lon": 11.77905}, {"type": "node", "id": 419496348, "lat": 18.322167, "lon": 11.7768}, {"type": "node", "id": 419496349, "lat": 18.32205, "lon": 11.774567}, {"type": "node", "id": 419496350, "lat": 18.3219, "lon": 11.772317}, {"type": "node", "id": 419496351, "lat": 18.321683, "lon": 11.7699}, {"type": "node", "id": 419496352, "lat": 18.321483, "lon": 11.767667}, {"type": "node", "id": 419496353, "lat": 18.321183, "lon": 11.765433}, {"type": "node", "id": 419496354, "lat": 18.3208, "lon": 11.763317}, {"type": "node", "id": 419496355, "lat": 18.320217, "lon": 11.760783}, {"type": "node", "id": 419496356, "lat": 18.319683, "lon": 11.758767}, {"type": "node", "id": 419496357, "lat": 18.319133, "lon": 11.756683}, {"type": "node", "id": 419496358, "lat": 18.318583, "lon": 11.7547}, {"type": "node", "id": 419496359, "lat": 18.318183, "lon": 11.752633}, {"type": "node", "id": 419496360, "lat": 18.317817, "lon": 11.750783}, {"type": "node", "id": 419496361, "lat": 18.31745, "lon": 11.74885}, {"type": "node", "id": 419496362, "lat": 18.317083, "lon": 11.746333}, {"type": "node", "id": 419496363, "lat": 18.316783, "lon": 11.7442}, {"type": "node", "id": 419496364, "lat": 18.316517, "lon": 11.742117}, {"type": "node", "id": 419496365, "lat": 18.316217, "lon": 11.740183}, {"type": "node", "id": 419496366, "lat": 18.315983, "lon": 11.738283}, {"type": "node", "id": 419496367, "lat": 18.3157, "lon": 11.73635}, {"type": "node", "id": 419496368, "lat": 18.31515, "lon": 11.734483}, {"type": "node", "id": 419496369, "lat": 18.314333, "lon": 11.732767}, {"type": "node", "id": 419496370, "lat": 18.313283, "lon": 11.731267}, {"type": "node", "id": 419496371, "lat": 18.3121, "lon": 11.729683}, {"type": "node", "id": 419496372, "lat": 18.310867, "lon": 11.728133}, {"type": "node", "id": 419496373, "lat": 18.309683, "lon": 11.7263}, {"type": "node", "id": 419496374, "lat": 18.30855, "lon": 11.724317}, {"type": "node", "id": 419496375, "lat": 18.307367, "lon": 11.722367}, {"type": "node", "id": 419496376, "lat": 18.305783, "lon": 11.720767}, {"type": "node", "id": 419496377, "lat": 18.30405, "lon": 11.71925}, {"type": "node", "id": 419496378, "lat": 18.30225, "lon": 11.7178}, {"type": "node", "id": 419496379, "lat": 18.300367, "lon": 11.7164}, {"type": "node", "id": 419496380, "lat": 18.298483, "lon": 11.715183}, {"type": "node", "id": 419496381, "lat": 18.296617, "lon": 11.71405}, {"type": "node", "id": 419496382, "lat": 18.294933, "lon": 11.7127}, {"type": "node", "id": 419496383, "lat": 18.2942, "lon": 11.71055}, {"type": "node", "id": 419496384, "lat": 18.2936, "lon": 11.708267}, {"type": "node", "id": 419496385, "lat": 18.2933, "lon": 11.705983}, {"type": "node", "id": 419496386, "lat": 18.292783, "lon": 11.7028}, {"type": "node", "id": 419496387, "lat": 18.292433, "lon": 11.700533}, {"type": "node", "id": 419496388, "lat": 18.292117, "lon": 11.698283}, {"type": "node", "id": 419496389, "lat": 18.291833, "lon": 11.696067}, {"type": "node", "id": 419496390, "lat": 18.291583, "lon": 11.693883}, {"type": "node", "id": 419496391, "lat": 18.291417, "lon": 11.6917}, {"type": "node", "id": 419496392, "lat": 18.291133, "lon": 11.6896}, {"type": "node", "id": 419496394, "lat": 18.290667, "lon": 11.687517}, {"type": "node", "id": 419496395, "lat": 18.290233, "lon": 11.6854}, {"type": "node", "id": 419496396, "lat": 18.2899, "lon": 11.683267}, {"type": "node", "id": 419496397, "lat": 18.289617, "lon": 11.681167}, {"type": "node", "id": 419496398, "lat": 18.289483, "lon": 11.679283}, {"type": "node", "id": 419496399, "lat": 18.2898, "lon": 11.677483}, {"type": "node", "id": 419496400, "lat": 18.289783, "lon": 11.675533}, {"type": "node", "id": 419496401, "lat": 18.289183, "lon": 11.67365}, {"type": "node", "id": 419496402, "lat": 18.288567, "lon": 11.671717}, {"type": "node", "id": 419496403, "lat": 18.28775, "lon": 11.6699}, {"type": "node", "id": 419496404, "lat": 18.286933, "lon": 11.668}, {"type": "node", "id": 419496405, "lat": 18.28605, "lon": 11.666133}, {"type": "node", "id": 419496406, "lat": 18.2854, "lon": 11.664217}, {"type": "node", "id": 419496407, "lat": 18.284317, "lon": 11.662867}, {"type": "node", "id": 419496408, "lat": 18.283217, "lon": 11.6632}, {"type": "node", "id": 419496409, "lat": 18.282633, "lon": 11.66465}, {"type": "node", "id": 419496410, "lat": 18.282183, "lon": 11.666383}, {"type": "node", "id": 419496411, "lat": 18.281817, "lon": 11.66825}, {"type": "node", "id": 419496412, "lat": 18.281417, "lon": 11.670133}, {"type": "node", "id": 419496413, "lat": 18.280583, "lon": 11.671533}, {"type": "node", "id": 419496414, "lat": 18.27985, "lon": 11.671183}, {"type": "node", "id": 419496415, "lat": 18.278567, "lon": 11.670383}, {"type": "node", "id": 419496416, "lat": 18.277367, "lon": 11.669133}, {"type": "node", "id": 419496417, "lat": 18.277233, "lon": 11.667517}, {"type": "node", "id": 419496418, "lat": 18.2776, "lon": 11.665817}, {"type": "node", "id": 419496419, "lat": 18.277467, "lon": 11.664333}, {"type": "node", "id": 419496420, "lat": 18.277067, "lon": 11.66405}, {"type": "node", "id": 419496421, "lat": 18.276, "lon": 11.664117}, {"type": "node", "id": 419496422, "lat": 18.2747, "lon": 11.6631}, {"type": "node", "id": 419496423, "lat": 18.27375, "lon": 11.661567}, {"type": "node", "id": 419496424, "lat": 18.27265, "lon": 11.66}, {"type": "node", "id": 419496425, "lat": 18.271417, "lon": 11.658333}, {"type": "node", "id": 419496427, "lat": 18.270217, "lon": 11.656983}, {"type": "node", "id": 419496428, "lat": 18.26895, "lon": 11.656683}, {"type": "node", "id": 419496429, "lat": 18.2672, "lon": 11.65675}, {"type": "node", "id": 419496430, "lat": 18.2658, "lon": 11.656883}, {"type": "node", "id": 419496431, "lat": 18.265067, "lon": 11.656633}, {"type": "node", "id": 419496432, "lat": 18.263983, "lon": 11.655583}, {"type": "node", "id": 419496433, "lat": 18.26315, "lon": 11.654183}, {"type": "node", "id": 419496434, "lat": 18.262683, "lon": 11.652333}, {"type": "node", "id": 419496435, "lat": 18.262283, "lon": 11.651217}, {"type": "node", "id": 419496436, "lat": 18.261567, "lon": 11.65045}, {"type": "node", "id": 419496437, "lat": 18.261, "lon": 11.649883}, {"type": "node", "id": 419496438, "lat": 18.260767, "lon": 11.64865}, {"type": "node", "id": 419496439, "lat": 18.260667, "lon": 11.646583}, {"type": "node", "id": 419496440, "lat": 18.260667, "lon": 11.64515}, {"type": "node", "id": 419496441, "lat": 18.260733, "lon": 11.643483}, {"type": "node", "id": 419496442, "lat": 18.2609, "lon": 11.642417}, {"type": "node", "id": 419496443, "lat": 18.2607, "lon": 11.641367}, {"type": "node", "id": 419496444, "lat": 18.25995, "lon": 11.640267}, {"type": "node", "id": 419496445, "lat": 18.2596, "lon": 11.63915}, {"type": "node", "id": 419496446, "lat": 18.25945, "lon": 11.638233}, {"type": "node", "id": 419496447, "lat": 18.25875, "lon": 11.636983}, {"type": "node", "id": 419496448, "lat": 18.257483, "lon": 11.635867}, {"type": "node", "id": 419496449, "lat": 18.256433, "lon": 11.6344}, {"type": "node", "id": 419496450, "lat": 18.2545, "lon": 11.631567}, {"type": "node", "id": 419496451, "lat": 18.253233, "lon": 11.629767}, {"type": "node", "id": 419496452, "lat": 18.2522, "lon": 11.628483}, {"type": "node", "id": 419496453, "lat": 18.25095, "lon": 11.627317}, {"type": "node", "id": 419496454, "lat": 18.249717, "lon": 11.626033}, {"type": "node", "id": 419496455, "lat": 18.24845, "lon": 11.625}, {"type": "node", "id": 419496456, "lat": 18.247, "lon": 11.624583}, {"type": "node", "id": 419496457, "lat": 18.245917, "lon": 11.624383}, {"type": "node", "id": 419496458, "lat": 18.244967, "lon": 11.623833}, {"type": "node", "id": 419496459, "lat": 18.24405, "lon": 11.62395}, {"type": "node", "id": 419496460, "lat": 18.243433, "lon": 11.623783}, {"type": "node", "id": 419496461, "lat": 18.2432, "lon": 11.623233}, {"type": "node", "id": 419496462, "lat": 18.243067, "lon": 11.622533}, {"type": "node", "id": 419496463, "lat": 18.242533, "lon": 11.622033}, {"type": "node", "id": 419496464, "lat": 18.2419, "lon": 11.621567}, {"type": "node", "id": 419496465, "lat": 18.241117, "lon": 11.621483}, {"type": "node", "id": 419496466, "lat": 18.2404, "lon": 11.621633}, {"type": "node", "id": 419496467, "lat": 18.240267, "lon": 11.621567}, {"type": "node", "id": 419496468, "lat": 18.24, "lon": 11.621217}, {"type": "node", "id": 419496469, "lat": 18.239883, "lon": 11.62085}, {"type": "node", "id": 419496470, "lat": 18.239417, "lon": 11.620467}, {"type": "node", "id": 419496471, "lat": 18.238983, "lon": 11.62}, {"type": "node", "id": 419496472, "lat": 18.237367, "lon": 11.619233}, {"type": "node", "id": 419496473, "lat": 18.2357, "lon": 11.618283}, {"type": "node", "id": 419496474, "lat": 18.234767, "lon": 11.616817}, {"type": "node", "id": 419496475, "lat": 18.234567, "lon": 11.616167}, {"type": "node", "id": 419496476, "lat": 18.23475, "lon": 11.615717}, {"type": "node", "id": 419496477, "lat": 18.234417, "lon": 11.615133}, {"type": "node", "id": 419496478, "lat": 18.234183, "lon": 11.6148}, {"type": "node", "id": 419496479, "lat": 18.233633, "lon": 11.614483}, {"type": "node", "id": 419496480, "lat": 18.232733, "lon": 11.613617}, {"type": "node", "id": 419496481, "lat": 18.231367, "lon": 11.61265}, {"type": "node", "id": 419496482, "lat": 18.2305, "lon": 11.611933}, {"type": "node", "id": 419496483, "lat": 18.229333, "lon": 11.610867}, {"type": "node", "id": 419496484, "lat": 18.2283, "lon": 11.609467}, {"type": "node", "id": 419496485, "lat": 18.2277, "lon": 11.6083}, {"type": "node", "id": 419496486, "lat": 18.227933, "lon": 11.6078}, {"type": "node", "id": 419496487, "lat": 18.228417, "lon": 11.60705}, {"type": "node", "id": 419496488, "lat": 18.228867, "lon": 11.606233}, {"type": "node", "id": 419496489, "lat": 18.2288, "lon": 11.605817}, {"type": "node", "id": 419496490, "lat": 18.228567, "lon": 11.60525}, {"type": "node", "id": 419496491, "lat": 18.228117, "lon": 11.604733}, {"type": "node", "id": 419496492, "lat": 18.2275, "lon": 11.605083}, {"type": "node", "id": 419496493, "lat": 18.226883, "lon": 11.605217}, {"type": "node", "id": 419496494, "lat": 18.226117, "lon": 11.605133}, {"type": "node", "id": 419496495, "lat": 18.2253, "lon": 11.605333}, {"type": "node", "id": 419496497, "lat": 18.224217, "lon": 11.6049}, {"type": "node", "id": 419496498, "lat": 18.223133, "lon": 11.6044}, {"type": "node", "id": 419496499, "lat": 18.222083, "lon": 11.603683}, {"type": "node", "id": 419496500, "lat": 18.22095, "lon": 11.602717}, {"type": "node", "id": 419496501, "lat": 18.219933, "lon": 11.6019}, {"type": "node", "id": 419496502, "lat": 18.2191, "lon": 11.600967}, {"type": "node", "id": 419496503, "lat": 18.21815, "lon": 11.600017}, {"type": "node", "id": 419496504, "lat": 18.217017, "lon": 11.599083}, {"type": "node", "id": 419496511, "lat": 18.2141902, "lon": 11.5987331}, {"type": "node", "id": 419496690, "lat": 18.4410325, "lon": 12.1348906}, {"type": "node", "id": 469916053, "lat": 17.5347517, "lon": 9.1189796}, {"type": "node", "id": 4927076274, "lat": 18.0311424, "lon": 10.1119563}, {"type": "node", "id": 4927076276, "lat": 18.1908727, "lon": 10.6756064}, {"type": "node", "id": 4927076277, "lat": 17.8431638, "lon": 9.6802279}, {"type": "node", "id": 4927076278, "lat": 18.6348636, "lon": 12.4086138}, {"type": "node", "id": 4927076280, "lat": 18.6318543, "lon": 12.3862978}, {"type": "node", "id": 4927076282, "lat": 18.6175392, "lon": 12.3317954}, {"type": "node", "id": 4927076283, "lat": 18.6133095, "lon": 12.3118826}, {"type": "node", "id": 4927076285, "lat": 18.6129842, "lon": 12.305102}, {"type": "node", "id": 4927076287, "lat": 18.6032229, "lon": 12.2548911}, {"type": "node", "id": 4927076289, "lat": 18.5889868, "lon": 12.2073409}, {"type": "node", "id": 4927076291, "lat": 18.5895562, "lon": 12.1769568}, {"type": "node", "id": 4927076293, "lat": 18.5815835, "lon": 12.1387621}, {"type": "node", "id": 4927076294, "lat": 18.5768648, "lon": 12.0998808}, {"type": "node", "id": 4927076296, "lat": 18.5749121, "lon": 12.0895812}, {"type": "node", "id": 4927076298, "lat": 18.5603482, "lon": 12.0553347}, {"type": "node", "id": 4927076299, "lat": 18.5458643, "lon": 12.0016905}, {"type": "node", "id": 4927076300, "lat": 18.5282053, "lon": 11.9474455}, {"type": "node", "id": 4927076302, "lat": 18.5230782, "lon": 11.9418665}, {"type": "node", "id": 4927076304, "lat": 18.5143699, "lon": 11.9126841}, {"type": "node", "id": 4927076305, "lat": 18.4963821, "lon": 11.8740603}, {"type": "node", "id": 4927076307, "lat": 18.4925564, "lon": 11.8520876}, {"type": "node", "id": 4927076310, "lat": 18.4732638, "lon": 11.7376753}, {"type": "node", "id": 4927076312, "lat": 18.457877, "lon": 11.6808554}, {"type": "node", "id": 4927076313, "lat": 18.4380105, "lon": 11.6218897}, {"type": "node", "id": 4927076314, "lat": 18.4192818, "lon": 11.5459296}, {"type": "node", "id": 4927076315, "lat": 18.4175717, "lon": 11.5140864}, {"type": "node", "id": 4927076316, "lat": 18.4170016, "lon": 11.5145155}, {"type": "node", "id": 4927076317, "lat": 18.4100796, "lon": 11.4837882}, {"type": "node", "id": 4927076318, "lat": 18.3952572, "lon": 11.4419886}, {"type": "node", "id": 4927076319, "lat": 18.3924066, "lon": 11.4213034}, {"type": "node", "id": 4927076320, "lat": 18.3952572, "lon": 11.4031931}, {"type": "node", "id": 4927078421, "lat": 18.3954201, "lon": 11.3981291}, {"type": "node", "id": 4927078422, "lat": 18.3792118, "lon": 11.34191}, {"type": "node", "id": 4927078423, "lat": 18.373673, "lon": 11.3256022}, {"type": "node", "id": 4927078424, "lat": 18.3647941, "lon": 11.2935015}, {"type": "node", "id": 4927078425, "lat": 18.3647941, "lon": 11.2703272}, {"type": "node", "id": 4927078426, "lat": 18.3559963, "lon": 11.2293002}, {"type": "node", "id": 4927078427, "lat": 18.3502123, "lon": 11.2212321}, {"type": "node", "id": 4927078428, "lat": 18.3436134, "lon": 11.1947962}, {"type": "node", "id": 4927078429, "lat": 18.3376661, "lon": 11.1836382}, {"type": "node", "id": 4927078430, "lat": 18.3173783, "lon": 11.1146304}, {"type": "node", "id": 4927078431, "lat": 18.3052371, "lon": 11.0551497}, {"type": "node", "id": 4927078432, "lat": 18.293747, "lon": 11.0217616}, {"type": "node", "id": 4927078433, "lat": 18.270357, "lon": 10.9099242}, {"type": "node", "id": 4927078434, "lat": 18.2631845, "lon": 10.8643481}, {"type": "node", "id": 4927078435, "lat": 18.247942, "lon": 10.8222052}, {"type": "node", "id": 4927078436, "lat": 18.2442738, "lon": 10.8049532}, {"type": "node", "id": 4927078437, "lat": 17.5672883, "lon": 9.1806075}, {"type": "node", "id": 4927078438, "lat": 17.5539499, "lon": 9.1522833}, {"type": "node", "id": 4927078439, "lat": 17.5185123, "lon": 9.0831896}, {"type": "node", "id": 4927078440, "lat": 17.5005045, "lon": 9.042935}, {"type": "node", "id": 4927078441, "lat": 17.4917455, "lon": 9.0308329}, {"type": "node", "id": 4927078442, "lat": 17.4906813, "lon": 9.0305754}, {"type": "node", "id": 4927078451, "lat": 18.1857355, "lon": 10.6501147}, {"type": "node", "id": 4927078452, "lat": 18.1834523, "lon": 10.6084868}, {"type": "node", "id": 4927078454, "lat": 18.1653484, "lon": 10.538449}, {"type": "node", "id": 4927078455, "lat": 18.1571114, "lon": 10.5131289}, {"type": "node", "id": 4927078457, "lat": 18.1459378, "lon": 10.4846331}, {"type": "node", "id": 4927078459, "lat": 18.1380261, "lon": 10.4533049}, {"type": "node", "id": 4927078460, "lat": 18.1177966, "lon": 10.4021498}, {"type": "node", "id": 4927078462, "lat": 17.8222468, "lon": 9.6319052}, {"type": "node", "id": 4927078474, "lat": 18.6859318, "lon": 12.6149508}, {"type": "node", "id": 4927078475, "lat": 18.6674742, "lon": 12.765927}, {"type": "node", "id": 4927078477, "lat": 18.6629205, "lon": 12.7461859}, {"type": "node", "id": 4927078478, "lat": 17.4830679, "lon": 9.0223357}, {"type": "node", "id": 4927078479, "lat": 18.6731662, "lon": 12.7224967}, {"type": "node", "id": 4927078481, "lat": 18.6761747, "lon": 12.7194926}, {"type": "node", "id": 4927078483, "lat": 18.6830047, "lon": 12.6958891}, {"type": "node", "id": 4927078484, "lat": 18.3078447, "lon": 11.0701701}, {"type": "node", "id": 4927078487, "lat": 18.6779635, "lon": 12.5905749}, {"type": "node", "id": 4927078488, "lat": 18.6621886, "lon": 12.5475737}, {"type": "node", "id": 4927078491, "lat": 18.6521049, "lon": 12.4892947}, {"type": "node", "id": 4927078493, "lat": 18.6386861, "lon": 12.4321314}, {"type": "node", "id": 4927078494, "lat": 18.6361649, "lon": 12.4086138}, {"type": "node", "id": 4927078496, "lat": 18.1045809, "lon": 10.3710791}, {"type": "node", "id": 4927078498, "lat": 18.0909563, "lon": 10.3395793}, {"type": "node", "id": 4927078499, "lat": 18.0654175, "lon": 10.2377841}, {"type": "node", "id": 4927078502, "lat": 18.0364473, "lon": 10.1292082}, {"type": "node", "id": 4927078505, "lat": 18.0281226, "lon": 10.0904986}, {"type": "node", "id": 4927078506, "lat": 17.8987901, "lon": 9.7911383}, {"type": "node", "id": 4927078507, "lat": 18.0220829, "lon": 10.0765082}, {"type": "node", "id": 4927078508, "lat": 18.2916282, "lon": 10.9980723}, {"type": "node", "id": 4927078511, "lat": 18.053422, "lon": 10.1999327}, {"type": "node", "id": 4927078512, "lat": 18.2157409, "lon": 10.730538}, {"type": "node", "id": 4927078514, "lat": 18.6542193, "lon": 12.5094649}, {"type": "node", "id": 4927078515, "lat": 18.01841, "lon": 10.0698992}, {"type": "node", "id": 4927078517, "lat": 17.9980034, "lon": 10.0427767}, {"type": "node", "id": 4927078519, "lat": 17.9895953, "lon": 10.029473}, {"type": "node", "id": 4927078520, "lat": 17.9760393, "lon": 10.0055434}, {"type": "node", "id": 4927078722, "lat": 17.969512, "lon": 9.9923941}, {"type": "node", "id": 4927078724, "lat": 17.9631437, "lon": 9.9809786}, {"type": "node", "id": 4927078725, "lat": 17.9569384, "lon": 9.9627825}, {"type": "node", "id": 4927078727, "lat": 17.9487732, "lon": 9.9428698}, {"type": "node", "id": 4927078729, "lat": 17.9372597, "lon": 9.9170348}, {"type": "node", "id": 4927078730, "lat": 17.9210089, "lon": 9.8898264}, {"type": "node", "id": 4927078731, "lat": 17.9206822, "lon": 9.8446795}, {"type": "node", "id": 4927078732, "lat": 17.9181505, "lon": 9.8340365}, {"type": "node", "id": 4927078733, "lat": 17.9152105, "lon": 9.8306891}, {"type": "node", "id": 4927078734, "lat": 17.9101469, "lon": 9.8136088}, {"type": "node", "id": 4927078735, "lat": 17.9014895, "lon": 9.8007342}, {"type": "node", "id": 4927078736, "lat": 17.888662, "lon": 9.7712256}, {"type": "node", "id": 4927078737, "lat": 17.8844186, "lon": 9.7580763}, {"type": "node", "id": 4927078738, "lat": 17.8189783, "lon": 9.624438}, {"type": "node", "id": 4927078739, "lat": 17.805822, "lon": 9.5996329}, {"type": "node", "id": 4927078740, "lat": 17.7923378, "lon": 9.5632407}, {"type": "node", "id": 4927078742, "lat": 17.7857138, "lon": 9.5229174}, {"type": "node", "id": 4927078743, "lat": 17.7795064, "lon": 9.4926878}, {"type": "node", "id": 4927078744, "lat": 17.7767235, "lon": 9.4872977}, {"type": "node", "id": 4927078745, "lat": 17.7714149, "lon": 9.454579}, {"type": "node", "id": 4927078746, "lat": 17.767982, "lon": 9.4432494}, {"type": "node", "id": 4927078747, "lat": 17.767324, "lon": 9.434426}, {"type": "node", "id": 4927078748, "lat": 17.7540004, "lon": 9.4184615}, {"type": "node", "id": 4927078749, "lat": 17.7443585, "lon": 9.4150111}, {"type": "node", "id": 4927078750, "lat": 17.731769, "lon": 9.3923518}, {"type": "node", "id": 4927078751, "lat": 17.7259644, "lon": 9.3746707}, {"type": "node", "id": 4927078752, "lat": 17.6102428, "lon": 9.2425772}, {"type": "node", "id": 4927078753, "lat": 17.6022254, "lon": 9.2315051}, {"type": "node", "id": 4927078754, "lat": 17.5883986, "lon": 9.2146822}, {"type": "node", "id": 4927078755, "lat": 17.8777204, "lon": 9.7414252}, {"type": "node", "id": 4927078756, "lat": 18.488812, "lon": 11.8252226}, {"type": "node", "id": 4927078758, "lat": 18.5969592, "lon": 12.2372958}, {"type": "node", "id": 4927078759, "lat": 17.8543566, "lon": 9.7009131}, {"type": "node", "id": 4927078762, "lat": 18.225035, "lon": 10.7544848}, {"type": "node", "id": 5054650813, "lat": 17.9511732, "lon": 9.9487227}, {"type": "node", "id": 5691385838, "lat": 17.4741757, "lon": 9.0140784}, {"type": "node", "id": 6129408604, "lat": 17.9512063, "lon": 9.9488034}, {"type": "node", "id": 9620696901, "lat": 18.6450329, "lon": 12.7264515}, {"type": "node", "id": 9620696902, "lat": 18.6448626, "lon": 12.7264971}, {"type": "node", "id": 9620696903, "lat": 18.6446339, "lon": 12.7264568}, {"type": "node", "id": 9620696904, "lat": 18.6445144, "lon": 12.7263442}, {"type": "node", "id": 9620696905, "lat": 18.6460355, "lon": 12.7259365}, {"type": "node", "id": 9620696906, "lat": 18.6465959, "lon": 12.7260625}, {"type": "node", "id": 9620696907, "lat": 18.6465501, "lon": 12.7259834}, {"type": "node", "id": 9620696908, "lat": 18.646437, "lon": 12.725907}, {"type": "node", "id": 9620696909, "lat": 18.6463227, "lon": 12.7258936}, {"type": "way", "id": 35894247, "nodes": [419495538, 419495781, 419495782, 419495783, 419495784, 419495785, 419495786, 419495787, 419495788, 419495789, 419495790, 419495791, 419495792, 419495793, 419495794, 419495795, 419495796, 419495797, 419495798, 419495799, 419495800, 419495801, 419495802, 419495803, 419495804, 419495805, 419495806, 419495807, 419495808, 419495809, 419495810, 9620696906, 9620696907, 419495811, 9620696908, 9620696909, 419495812, 9620696905, 419495813, 9620696901, 9620696902, 419495814, 9620696903, 9620696904, 419495815, 419495816, 419495817, 419495818, 419495819, 419495820, 419495821, 419495822, 419495823, 419495824, 419495825, 419495826, 419495827, 419495828, 419495829, 419495830, 419495831, 419495832, 419495833, 419495834, 419495835, 419495836, 419495837, 419495838, 419495839, 419495840, 419495841, 419495842, 419495843, 419495844, 419495845, 419495846, 419495847, 419495848, 419495849, 419495850, 419495851, 419495852, 419495853, 419495854, 419495855, 419495856, 419495857, 419495858, 419495859, 419495860, 419495861, 419495862, 419495863, 419495864, 419495865, 419495866, 419495867, 419495868, 419495869, 419495870, 419495871, 419495872, 419495873, 419495874, 419495875, 419495876, 419495877, 419495887, 419495888, 419495889, 419495890, 419495891, 419495892, 419495893, 419495894, 419495895, 419495896, 419495897, 419495898, 419495899, 419495900, 419495901, 419495902, 419495903, 419495904, 419495905, 419495906, 419495907, 419495908, 419495909, 419495910, 419495911, 419495912, 419495913, 419495914, 419495915, 419495916, 419495917, 419495918, 419495919, 419495920, 419495921, 419495922, 419495929, 419495930, 419495931, 419495932, 419495933, 419495934, 419495935, 419495936, 419495937, 419495938, 419495939, 419495940, 419495941, 419495942, 419495943, 419495944, 419495945, 419495946, 419495947, 419495948, 419495949, 419495950, 419495951, 419495952, 419495953, 419495954, 419495955, 419495956, 419495957, 419495958, 419495959, 419495961, 419495962, 419495963, 419495965, 419495967, 419495970, 419495972, 419495974, 419495976, 419495978, 419495980, 419495982, 419495984, 419495986, 419495988, 419495990, 419495992, 419495994, 419495996], "tags": {"highway": "primary", "name": "\u0637 \u0648 \u0665\u0666", "name:ar": "\u0637 \u0648 \u0665\u0666", "name:en": "N56", "ref": "N56", "surface": "unpaved"}}, {"type": "way", "id": 35894251, "nodes": [419496690, 419496204, 419496205, 419496206, 419496207, 419496208, 419496209, 419496210, 419496211, 419496212, 419496213, 419496214, 419496215, 419496216, 419496217, 419496218, 419496219, 419496220, 419496221, 419496222, 419496223, 419496224, 419496225, 419496226, 419496227, 419496228, 419496229, 419496230, 419496231, 419496232, 419496233, 419496234, 419496235, 419496236, 419496237, 419496238, 419496239, 419496240, 419496241, 419496242, 419496243, 419496244, 419496245, 419496246, 419496247, 419496248, 419496249, 419496250, 419496251, 419496252, 419496253, 419496254, 419496255, 419496256, 419496257, 419496258, 419496259, 419496260, 419496261, 419496262, 419496263, 419496264, 419496265, 419496266, 419496267, 419496268, 419496269, 419496270, 419496271, 419496272, 419496273, 419496274, 419496275, 419496276, 419496277, 419496278, 419496279, 419496280, 419496281, 419496282, 419496283, 419496284, 419496285, 419496286, 419496287, 419496288, 419496289, 419496290, 419496291, 419496292, 419496293, 419496294, 419496295, 419496296, 419496297, 419496298, 419496299, 419496300, 419496301, 419496302, 419496303, 419496304, 419496305, 419496306, 419496307, 419496308, 419496309, 419496310, 419496311, 419496312, 419496313, 419496314, 419496315, 419496316, 419496317, 419496318, 419496319, 419496320, 419496321, 419496322, 419496323, 419496324, 419496325, 419496326, 419496327, 419496328, 419496329, 419496330, 419496331, 419496333, 419496334, 419496335, 419496336, 419496337, 419496338, 419496339, 419496340, 419496341, 419496342, 419496343, 419496344, 419496345, 419496346, 419496347, 419496348, 419496349, 419496350, 419496351, 419496352, 419496353, 419496354, 419496355, 419496356, 419496357, 419496358, 419496359, 419496360, 419496361, 419496362, 419496363, 419496364, 419496365, 419496366, 419496367, 419496368, 419496369, 419496370, 419496371, 419496372, 419496373, 419496374, 419496375, 419496376, 419496377, 419496378, 419496379, 419496380, 419496381, 419496382, 419496383, 419496384, 419496385, 419496386, 419496387, 419496388, 419496389, 419496390, 419496391, 419496392, 419496394, 419496395, 419496396, 419496397, 419496398, 419496399, 419496400, 419496401, 419496402, 419496403, 419496404, 419496405, 419496406, 419496407, 419496408, 419496409, 419496410, 419496411, 419496412, 419496413, 419496414, 419496415, 419496416, 419496417, 419496418, 419496419, 419496420, 419496421, 419496422, 419496423, 419496424, 419496425, 419496427, 419496428, 419496429, 419496430, 419496431, 419496432, 419496433, 419496434, 419496435, 419496436, 419496437, 419496438, 419496439, 419496440, 419496441, 419496442, 419496443, 419496444, 419496445, 419496446, 419496447, 419496448, 419496449, 419496450, 419496451, 419496452, 419496453, 419496454, 419496455, 419496456, 419496457, 419496458, 419496459, 419496460, 419496461, 419496462, 419496463, 419496464, 419496465, 419496466, 419496467, 419496468, 419496469, 419496470, 419496471, 419496472, 419496473, 419496474, 419496475, 419496476, 419496477, 419496478, 419496479, 419496480, 419496481, 419496482, 419496483, 419496484, 419496485, 419496486, 419496487, 419496488, 419496489, 419496490, 419496491, 419496492, 419496493, 419496494, 419496495, 419496497, 419496498, 419496499, 419496500, 419496501, 419496502, 419496503, 419496504, 419496511], "tags": {"highway": "primary", "surface": "unpaved"}}, {"type": "way", "id": 35894252, "nodes": [419496690, 419496197, 419496198, 419496199, 419496200, 419496201, 419496202, 419496203], "tags": {"highway": "track"}}, {"type": "way", "id": 35894253, "nodes": [419495996, 419495998, 419496000, 419496002, 419496005, 419496006, 419496015, 419496017, 419496019, 419496021, 419496022, 419496024, 419496026, 419496028, 419496031, 419496033, 419496035, 419496037, 419496039, 419496041, 419496043, 419496045, 419496047, 419496049, 419496051, 419496053, 419496055, 419496057, 419496059, 419496061, 419496063, 419496071, 419496074, 419496076, 419496077, 419496078, 419496079, 419496080, 419496081, 419496082, 419496083, 419496084, 419496085, 419496087, 419496089, 419496091, 419496093, 419496095, 419496097, 419496099, 419496101, 419496103, 419496105, 419496107, 419496109, 419496111, 419496113, 419496117, 419496118, 419496119, 419496120, 419496121, 419496122, 419496123, 419496124, 419496125, 419496126, 419496127, 419496128, 419496129, 419496130, 419496131, 419496132, 419496133, 419496134, 419496135, 419496136, 419496137, 419496138, 419496139, 419496140, 419496141, 419496142, 419496143, 419496144, 419496145, 419496146, 419496147, 419496148, 419496149, 419496150, 419496151, 419496152, 419496153, 419496154, 419496155, 419496156, 419496157, 419496158, 419496159, 419496160, 419496161, 419496162, 419496163, 419496164, 419496165, 419496166, 419496167, 419496168, 419496169, 419496170, 419496171, 419496172, 419496173, 419496174, 419496175, 419496176, 419496177, 419496178, 419496179, 419496180, 419496181, 419496182, 419496183, 419496184, 419496185, 419496186, 419496187, 419496188, 419496189, 419496190, 419496191, 419496192, 419496193, 419496194, 419496195, 419496196, 419496690], "tags": {"highway": "primary", "surface": "unpaved"}}, {"type": "way", "id": 695665230, "nodes": [5691385838, 4927078478, 4927078442, 4927078441, 4927078440, 4927078439, 469916053, 4927078438, 4927078437, 4927078754, 4927078753, 4927078752, 4927078751, 4927078750, 4927078749, 4927078748, 4927078747, 4927078746, 4927078745, 4927078744, 4927078743, 4927078742, 4927078740, 4927078739, 4927078738, 4927078462, 4927076277, 4927078759, 4927078755, 4927078737, 4927078736, 4927078506, 4927078735, 4927078734, 4927078733, 4927078732, 4927078731, 4927078730, 4927078729, 4927078727, 5054650813, 6129408604, 4927078725, 4927078724, 4927078722, 4927078520, 4927078519, 4927078517, 4927078515, 4927078507, 4927078505, 4927076274, 4927078502, 4927078511, 4927078499, 4927078498, 4927078496, 4927078460, 4927078459, 4927078457, 4927078455, 4927078454, 4927078452, 4927078451, 4927076276, 4927078512, 4927078762, 4927078436, 4927078435, 4927078434, 4927078433, 4927078508, 4927078432, 4927078431, 4927078484, 4927078430, 4927078429, 4927078428, 4927078427, 4927078426, 4927078425, 4927078424, 4927078423, 4927078422, 4927078421, 4927076320, 4927076319, 4927076318, 4927076317, 4927076316, 4927076315, 4927076314, 4927076313, 4927076312, 4927076310, 4927078756, 4927076307, 4927076305, 4927076304, 4927076302, 4927076300, 4927076299, 4927076298, 4927076296, 4927076294, 4927076293, 4927076291, 4927076289, 4927078758, 4927076287, 4927076285, 4927076283, 4927076282, 4927076280, 4927076278, 4927078494, 4927078493, 4927078491, 4927078514, 4927078488, 4927078487, 4927078474, 4927078483, 4927078481, 4927078479, 4927078477, 4927078475, 419495786], "tags": {"highway": "unclassified", "int_ref": "TAH 3", "surface": "unpaved"}}]}